{"title":"Exercise 10.1.1a","markdown":{"yaml":{"title":"Exercise 10.1.1a","author":"Nathan Lunceford","format":{"html":{"self-contained":true,"page-layout":"full","toc":true,"toc-depth":1,"toc-location":"right","number-sections":false,"html-math-method":"katex","embed-resources":true,"code-fold":true,"code-summary":"Show the code","code-overflow":"wrap","code-copy":"hover","code-tools":{"source":false,"toggle":true,"caption":"See code"}}},"engine":"jupyter","preview":{"port":3000,"browser":false,"watch-inputs":true}},"headingText":"**Problem:**","containsRefs":false,"markdown":"\n\n\n::: {.callout-note icon=false }\n\n## **10.1.1a**\n\nFind the Discrete Fourier Transform (DFT) of the following vector:\n\n$$\n\\begin{bmatrix}\n0 \\\\ 1 \\\\ 0 \\\\ -1\n\\end{bmatrix}\n$$\n\n:::\n\n# **Solution:**\n\n### **Compute the DFT using the matrix formulation:**\n\n$$\n\\mathbf{y} = F \\mathbf{x}\n$$\n\nWhere:\n\n- $F$ is the Fourier matrix, with entries:\n  $$\n  F_{k,j} = \\omega^{k j}, \\quad \\omega = e^{-i \\frac{2\\pi}{n}}\n  $$\n- $\\mathbf{x} = \\begin{bmatrix} x_0 \\\\ x_1 \\\\ x_2 \\\\ x_3 \\end{bmatrix}$ is the input vector\n\n\\vspace{.25cm}\n\n- $\\mathbf{y} = \\begin{bmatrix} y_0 \\\\ y_1 \\\\ y_2 \\\\ y_3 \\end{bmatrix}$ is the DFT of the input vector\n\n### **Define Parameters**\n\nThe input vector is:\n\n$$\n\\mathbf{x} = \\begin{bmatrix} 0 \\\\ 1 \\\\ 0 \\\\ -1 \\end{bmatrix}\n$$\n\nThe length of the vector is $n = 4$. The primitive root of unity is:\n\n$$\n\\omega = e^{-i \\frac{2\\pi}{n}} = e^{-i \\frac{\\pi}{2}} = \\cos\\left(\\frac{\\pi}{2}\\right) - i \\sin\\left(\\frac{\\pi}{2}\\right) = -i\n$$\n\n### **Construct the Fourier Matrix $F_4$**\n\nThe Fourier matrix $F_4$ is given by:\n\n$$\nF_4 =\n\\begin{bmatrix}\n\\omega^{0 \\cdot 0} & \\omega^{0 \\cdot 1} & \\omega^{0 \\cdot 2} & \\omega^{0 \\cdot 3} \\\\\n\\omega^{1 \\cdot 0} & \\omega^{1 \\cdot 1} & \\omega^{1 \\cdot 2} & \\omega^{1 \\cdot 3} \\\\\n\\omega^{2 \\cdot 0} & \\omega^{2 \\cdot 1} & \\omega^{2 \\cdot 2} & \\omega^{2 \\cdot 3} \\\\\n\\omega^{3 \\cdot 0} & \\omega^{3 \\cdot 1} & \\omega^{3 \\cdot 2} & \\omega^{3 \\cdot 3}\n\\end{bmatrix}\n$$\n\n### **Compute Powers of $\\omega$**\n\n- $\\omega^0 = 1$\n- $\\omega^1 = -i$\n- $\\omega^2 = (-i)^2 = -1$\n- $\\omega^3 = (-i)^3 = i$\n\n#### **Fill in the Matrix $F_4$:**\n\n$$\nF_4 =\n\\begin{bmatrix}\n1 & 1 & 1 & 1 \\\\\n1 & -i & -1 & i \\\\\n1 & -1 & 1 & -1 \\\\\n1 & i & -1 & -i\n\\end{bmatrix}\n$$\n\n### **Perform the Matrix Multiplication**\n\n- **$y_0$:**\n\n  $$\n  y_0 = 1 \\cdot 0 + 1 \\cdot 1 + 1 \\cdot 0 + 1 \\cdot (-1) = 0 + 1 + 0 - 1 = 0\n  $$\n\n- **$y_1$:**\n\n  $$\n  y_1 = 1 \\cdot 0 + (-i) \\cdot 1 + (-1) \\cdot 0 + i \\cdot (-1)\n  $$\n\n  $$\n  y_1 = 0 - i + 0 - i = -2i\n  $$\n\n- **$y_2$:**\n\n  $$\n  y_2 = 1 \\cdot 0 + (-1) \\cdot 1 + 1 \\cdot 0 + (-1) \\cdot (-1)\n  $$\n\n  $$\n  y_2 = 0 - 1 + 0 + 1 = 0\n  $$\n\n- **$y_3$:**\n  $$\n  y_3 = 1 \\cdot 0 + i \\cdot 1 + (-1) \\cdot 0 + (-i) \\cdot (-1)\n  $$\n  $$\n  y_3 = 0 + i + 0 + i = 2i\n  $$\n\n::: {.callout-tip icon=false}\n\n## **Final Answer:**\n\nThe DFT of $\\mathbf{x}$ is:\n\n$$\n\\mathbf{y} = \\begin{bmatrix} 0 \\\\ -2i \\\\ 0 \\\\ 2i \\end{bmatrix}\n$$\n\n:::\n","srcMarkdownNoYaml":"\n\n# **Problem:**\n\n::: {.callout-note icon=false }\n\n## **10.1.1a**\n\nFind the Discrete Fourier Transform (DFT) of the following vector:\n\n$$\n\\begin{bmatrix}\n0 \\\\ 1 \\\\ 0 \\\\ -1\n\\end{bmatrix}\n$$\n\n:::\n\n# **Solution:**\n\n### **Compute the DFT using the matrix formulation:**\n\n$$\n\\mathbf{y} = F \\mathbf{x}\n$$\n\nWhere:\n\n- $F$ is the Fourier matrix, with entries:\n  $$\n  F_{k,j} = \\omega^{k j}, \\quad \\omega = e^{-i \\frac{2\\pi}{n}}\n  $$\n- $\\mathbf{x} = \\begin{bmatrix} x_0 \\\\ x_1 \\\\ x_2 \\\\ x_3 \\end{bmatrix}$ is the input vector\n\n\\vspace{.25cm}\n\n- $\\mathbf{y} = \\begin{bmatrix} y_0 \\\\ y_1 \\\\ y_2 \\\\ y_3 \\end{bmatrix}$ is the DFT of the input vector\n\n### **Define Parameters**\n\nThe input vector is:\n\n$$\n\\mathbf{x} = \\begin{bmatrix} 0 \\\\ 1 \\\\ 0 \\\\ -1 \\end{bmatrix}\n$$\n\nThe length of the vector is $n = 4$. The primitive root of unity is:\n\n$$\n\\omega = e^{-i \\frac{2\\pi}{n}} = e^{-i \\frac{\\pi}{2}} = \\cos\\left(\\frac{\\pi}{2}\\right) - i \\sin\\left(\\frac{\\pi}{2}\\right) = -i\n$$\n\n### **Construct the Fourier Matrix $F_4$**\n\nThe Fourier matrix $F_4$ is given by:\n\n$$\nF_4 =\n\\begin{bmatrix}\n\\omega^{0 \\cdot 0} & \\omega^{0 \\cdot 1} & \\omega^{0 \\cdot 2} & \\omega^{0 \\cdot 3} \\\\\n\\omega^{1 \\cdot 0} & \\omega^{1 \\cdot 1} & \\omega^{1 \\cdot 2} & \\omega^{1 \\cdot 3} \\\\\n\\omega^{2 \\cdot 0} & \\omega^{2 \\cdot 1} & \\omega^{2 \\cdot 2} & \\omega^{2 \\cdot 3} \\\\\n\\omega^{3 \\cdot 0} & \\omega^{3 \\cdot 1} & \\omega^{3 \\cdot 2} & \\omega^{3 \\cdot 3}\n\\end{bmatrix}\n$$\n\n### **Compute Powers of $\\omega$**\n\n- $\\omega^0 = 1$\n- $\\omega^1 = -i$\n- $\\omega^2 = (-i)^2 = -1$\n- $\\omega^3 = (-i)^3 = i$\n\n#### **Fill in the Matrix $F_4$:**\n\n$$\nF_4 =\n\\begin{bmatrix}\n1 & 1 & 1 & 1 \\\\\n1 & -i & -1 & i \\\\\n1 & -1 & 1 & -1 \\\\\n1 & i & -1 & -i\n\\end{bmatrix}\n$$\n\n### **Perform the Matrix Multiplication**\n\n- **$y_0$:**\n\n  $$\n  y_0 = 1 \\cdot 0 + 1 \\cdot 1 + 1 \\cdot 0 + 1 \\cdot (-1) = 0 + 1 + 0 - 1 = 0\n  $$\n\n- **$y_1$:**\n\n  $$\n  y_1 = 1 \\cdot 0 + (-i) \\cdot 1 + (-1) \\cdot 0 + i \\cdot (-1)\n  $$\n\n  $$\n  y_1 = 0 - i + 0 - i = -2i\n  $$\n\n- **$y_2$:**\n\n  $$\n  y_2 = 1 \\cdot 0 + (-1) \\cdot 1 + 1 \\cdot 0 + (-1) \\cdot (-1)\n  $$\n\n  $$\n  y_2 = 0 - 1 + 0 + 1 = 0\n  $$\n\n- **$y_3$:**\n  $$\n  y_3 = 1 \\cdot 0 + i \\cdot 1 + (-1) \\cdot 0 + (-i) \\cdot (-1)\n  $$\n  $$\n  y_3 = 0 + i + 0 + i = 2i\n  $$\n\n::: {.callout-tip icon=false}\n\n## **Final Answer:**\n\nThe DFT of $\\mathbf{x}$ is:\n\n$$\n\\mathbf{y} = \\begin{bmatrix} 0 \\\\ -2i \\\\ 0 \\\\ 2i \\end{bmatrix}\n$$\n\n:::\n"},"formats":{"html":{"identifier":{"display-name":"HTML","target-format":"html","base-format":"html"},"execute":{"fig-width":7,"fig-height":5,"fig-format":"retina","fig-dpi":96,"df-print":"default","error":false,"eval":true,"cache":null,"freeze":false,"echo":true,"output":true,"warning":true,"include":true,"keep-md":false,"keep-ipynb":false,"ipynb":null,"enabled":null,"daemon":null,"daemon-restart":false,"debug":false,"ipynb-filters":[],"ipynb-shell-interactivity":null,"plotly-connected":true,"engine":"jupyter"},"render":{"keep-tex":false,"keep-typ":false,"keep-source":false,"keep-hidden":false,"prefer-html":false,"output-divs":true,"output-ext":"html","fig-align":"default","fig-pos":null,"fig-env":null,"code-fold":true,"code-overflow":"wrap","code-link":false,"code-line-numbers":false,"code-tools":{"source":false,"toggle":true,"caption":"See code"},"tbl-colwidths":"auto","merge-includes":true,"inline-includes":false,"preserve-yaml":false,"latex-auto-mk":true,"latex-auto-install":true,"latex-clean":true,"latex-min-runs":1,"latex-max-runs":10,"latex-makeindex":"makeindex","latex-makeindex-opts":[],"latex-tlmgr-opts":[],"latex-input-paths":[],"latex-output-dir":null,"link-external-icon":false,"link-external-newwindow":false,"self-contained-math":false,"format-resources":[],"notebook-links":true},"pandoc":{"standalone":true,"wrap":"none","default-image-extension":"png","to":"html","css":["../../../../styles.css"],"toc":true,"self-contained":true,"toc-depth":1,"number-sections":false,"html-math-method":"katex","embed-resources":true,"output-file":"exercise10-1-1a.html"},"language":{"toc-title-document":"Table of contents","toc-title-website":"On this page","related-formats-title":"Other Formats","related-notebooks-title":"Notebooks","source-notebooks-prefix":"Source","other-links-title":"Other Links","code-links-title":"Code Links","launch-dev-container-title":"Launch Dev Container","launch-binder-title":"Launch Binder","article-notebook-label":"Article Notebook","notebook-preview-download":"Download Notebook","notebook-preview-download-src":"Download Source","notebook-preview-back":"Back to Article","manuscript-meca-bundle":"MECA Bundle","section-title-abstract":"Abstract","section-title-appendices":"Appendices","section-title-footnotes":"Footnotes","section-title-references":"References","section-title-reuse":"Reuse","section-title-copyright":"Copyright","section-title-citation":"Citation","appendix-attribution-cite-as":"For attribution, please cite this work as:","appendix-attribution-bibtex":"BibTeX citation:","appendix-view-license":"View License","title-block-author-single":"Author","title-block-author-plural":"Authors","title-block-affiliation-single":"Affiliation","title-block-affiliation-plural":"Affiliations","title-block-published":"Published","title-block-modified":"Modified","title-block-keywords":"Keywords","callout-tip-title":"Tip","callout-note-title":"Note","callout-warning-title":"Warning","callout-important-title":"Important","callout-caution-title":"Caution","code-summary":"Code","code-tools-menu-caption":"Code","code-tools-show-all-code":"Show All Code","code-tools-hide-all-code":"Hide All Code","code-tools-view-source":"View Source","code-tools-source-code":"Source Code","tools-share":"Share","tools-download":"Download","code-line":"Line","code-lines":"Lines","copy-button-tooltip":"Copy to Clipboard","copy-button-tooltip-success":"Copied!","repo-action-links-edit":"Edit this page","repo-action-links-source":"View source","repo-action-links-issue":"Report an issue","back-to-top":"Back to top","search-no-results-text":"No results","search-matching-documents-text":"matching documents","search-copy-link-title":"Copy link to search","search-hide-matches-text":"Hide additional matches","search-more-match-text":"more match in this document","search-more-matches-text":"more matches in this document","search-clear-button-title":"Clear","search-text-placeholder":"","search-detached-cancel-button-title":"Cancel","search-submit-button-title":"Submit","search-label":"Search","toggle-section":"Toggle section","toggle-sidebar":"Toggle sidebar navigation","toggle-dark-mode":"Toggle dark mode","toggle-reader-mode":"Toggle reader mode","toggle-navigation":"Toggle navigation","crossref-fig-title":"Figure","crossref-tbl-title":"Table","crossref-lst-title":"Listing","crossref-thm-title":"Theorem","crossref-lem-title":"Lemma","crossref-cor-title":"Corollary","crossref-prp-title":"Proposition","crossref-cnj-title":"Conjecture","crossref-def-title":"Definition","crossref-exm-title":"Example","crossref-exr-title":"Exercise","crossref-ch-prefix":"Chapter","crossref-apx-prefix":"Appendix","crossref-sec-prefix":"Section","crossref-eq-prefix":"Equation","crossref-lof-title":"List of Figures","crossref-lot-title":"List of Tables","crossref-lol-title":"List of Listings","environment-proof-title":"Proof","environment-remark-title":"Remark","environment-solution-title":"Solution","listing-page-order-by":"Order By","listing-page-order-by-default":"Default","listing-page-order-by-date-asc":"Oldest","listing-page-order-by-date-desc":"Newest","listing-page-order-by-number-desc":"High to Low","listing-page-order-by-number-asc":"Low to High","listing-page-field-date":"Date","listing-page-field-title":"Title","listing-page-field-description":"Description","listing-page-field-author":"Author","listing-page-field-filename":"File Name","listing-page-field-filemodified":"Modified","listing-page-field-subtitle":"Subtitle","listing-page-field-readingtime":"Reading Time","listing-page-field-wordcount":"Word Count","listing-page-field-categories":"Categories","listing-page-minutes-compact":"{0} min","listing-page-category-all":"All","listing-page-no-matches":"No matching items","listing-page-words":"{0} words","listing-page-filter":"Filter","draft":"Draft"},"metadata":{"lang":"en","fig-responsive":true,"quarto-version":"1.5.57","theme":{"light":"flatly","dark":"darkly"},"title":"Exercise 10.1.1a","author":"Nathan Lunceford","preview":{"port":3000,"browser":false,"watch-inputs":true},"page-layout":"full","toc-location":"right","code-summary":"Show the code","code-copy":"hover"},"extensions":{"book":{"multiFile":true}}}},"projectFormats":["html"]}